webrider_async/__init__.py
webrider_async/logger.py
webrider_async/user_agents_pool.txt
webrider_async/webrider_async.py
webrider_async-0.0.7.dist-info/LICENSE
webrider_async-0.0.7.dist-info/METADATA
webrider_async-0.0.7.dist-info/WHEEL
webrider_async-0.0.7.dist-info/top_level.txt
webrider_async-0.0.7.dist-info/RECORD
