Metadata-Version: 2.1
Name: webrider_async
Version: 0.0.7
Summary: A simple manager for async requests
Home-page: https://github.com/bogdan-sikorsky/webrider
Author: Bogdan Sikorsky
Author-email: <bogdan.sikorsky.dev@gmail.com>
Project-URL: Source, https://github.com/bogdan-sikorsky/webrider
Project-URL: Documentation, https://github.com/bogdan-sikorsky/webrider/README.md
Project-URL: Issues, https://github.com/bogdan-sikorsky/webrider/issues
Keywords: python,async,scraping,requests,aiohttp,asyncio
Classifier: Development Status :: 2 - Pre-Alpha
Classifier: Intended Audience :: Developers
Classifier: Programming Language :: Python :: 3
Classifier: Operating System :: Unix
Classifier: Operating System :: MacOS :: MacOS X
Classifier: Operating System :: Microsoft :: Windows
Classifier: Topic :: Utilities
Requires-Python: >=3.8
License-File: LICENSE
Requires-Dist: Brotli==1.1.0
Requires-Dist: aiohttp==3.10.5
Requires-Dist: certifi==2024.8.30
